{
    "name": "testTool",
    "description": "A test tool",
    "inputSchema": {
        "type": "object",
        "required": ["query_input1", "header_input2"],
        "contentType": "application/json",
        "properties": {
            "query_input1": {
                "type": "string",
                "description": "The first input"
            },
            "header_input2": {
                "type": "string",
                "description": "The second input"
            },
            "requestBody": {
                "type": "object",
                "description": "The request body",
                "required": [
                    "address",
                    "pizzaType",
                    "quantity"
                ],
                "properties": {
                    "customerName": {
                        "type": "string"
                    },
                    "delivered": {
                        "type": "boolean"
                    },
                    "address": {
                        "type": "string"
                    },
                    "pizzaType": {
                        "type": "string"
                    },
                    "creditCardNumber": {
                        "type": "string"
                    },
                    "quantity": {
                        "type": "number"
                    },
                    "orderId": {
                        "type": "string"
                    }
                }
            }
        }
    }
}